AUTHORS
CHANGELOG.txt
DESCRIPTION
LICENSE
MANIFEST.in
README.rst
setup.py
currency_history/__init__.py
currency_history/admin.py
currency_history/models.py
currency_history/management/__init__.py
currency_history/management/commands/__init__.py
currency_history/management/commands/track_currency_rates.py
currency_history/migrations/0001_initial.py
currency_history/migrations/0002_auto_20170804_0933.py
currency_history/migrations/0003_currencyratehistory_fixed.py
currency_history/migrations/0004_auto_20170830_1605.py
currency_history/migrations/__init__.py
currency_history/south_migrations/0001_initial.py
currency_history/south_migrations/__init__.py
currency_history/static/.empty
currency_history/static/currency_course/.empty
currency_history/templates/currency_history/.empty
currency_history/templates/currency_history/email/currency_email_report_body.html
currency_history/templates/currency_history/email/currency_email_report_subject.txt
currency_history/templatetags/__init__.py
currency_history/templatetags/currency_history_tags.py
currency_history/tests/__init__.py
currency_history/tests/management_tests.py
currency_history/tests/models_tests.py
currency_history/tests/settings.py
currency_history/tests/tags_tests.py
currency_history/tests/test_settings.py
currency_history/tests/urls.py
currency_history/tests/test_app/__init__.py
currency_history/tests/test_app/models.py
currency_history/tests/test_app/templates/400.html
currency_history/tests/test_app/templates/500.html
django_currency_history.egg-info/PKG-INFO
django_currency_history.egg-info/SOURCES.txt
django_currency_history.egg-info/dependency_links.txt
django_currency_history.egg-info/requires.txt
django_currency_history.egg-info/top_level.txt