Metadata-Version: 1.0
Name: django-currency-history
Version: 0.2.9
Summary: A reusable Django app that tracks currency rates.
